actigraph/__init__.py
actigraph-2018.10.1.dist-info/DESCRIPTION.rst
actigraph-2018.10.1.dist-info/LICENSE.txt
actigraph-2018.10.1.dist-info/METADATA
actigraph-2018.10.1.dist-info/RECORD
actigraph-2018.10.1.dist-info/WHEEL
actigraph-2018.10.1.dist-info/metadata.json
actigraph-2018.10.1.dist-info/top_level.txt
